<Properties StartupConfiguration="{7A5F8C70-6F4E-AFC0-0E30-D9A6D69D3F9E}|">
  <MonoDevelop.Ide.Workbench ActiveDocument="Assets/script/koma.cs">
    <Files>
      <File FileName="Assets/script/Motikinn.cs" Line="182" Column="55" />
      <File FileName="Assets/script/koma.cs" Line="224" Column="30" />
      <File FileName="Assets/script/Gamecontroller.cs" Line="334" Column="56" />
      <File FileName="Assets/script/SetPosition.cs" Line="90" Column="46" />
      <File FileName="Assets/script/Mapdata.cs" Line="11" Column="5" />
      <File FileName="Assets/script/TurnChange.cs" Line="26" Column="69" />
      <File FileName="Assets/script/FadeScript.cs" Line="28" Column="1" />
      <File FileName="Assets/script/memo.cs" Line="687" Column="112" />
      <File FileName="Assets/script/DebugMapdata.cs" Line="27" Column="17" />
    </Files>
  </MonoDevelop.Ide.Workbench>
  <MonoDevelop.Ide.DebuggingService.PinnedWatches />
  <MonoDevelop.Ide.Workspace ActiveConfiguration="Debug" />
  <MonoDevelop.Ide.ItemProperties.Assembly-CSharp PreferredExecutionTarget="Unity.Editor" />
  <MonoDevelop.Ide.DebuggingService.Breakpoints>
    <BreakpointStore />
  </MonoDevelop.Ide.DebuggingService.Breakpoints>
  <MultiItemStartupConfigurations />
</Properties>